pyairvisual/__init__.py
pyairvisual/air_quality.py
pyairvisual/cloud_api.py
pyairvisual/const.py
pyairvisual/errors.py
pyairvisual/node.py
pyairvisual/py.typed
pyairvisual/supported.py
pyairvisual-2023.12.0.dist-info/LICENSE
pyairvisual-2023.12.0.dist-info/METADATA
pyairvisual-2023.12.0.dist-info/WHEEL
pyairvisual-2023.12.0.dist-info/RECORD
